CHANGELOG.md
LICENSE
ifpd/__init__.py
ifpd/bioext.py
ifpd/const.py
ifpd/exception.py
ifpd/interface/css/bootstrap.min.css
ifpd/interface/css/font-awesome.min.css
ifpd/interface/css/fonts.css
ifpd/interface/css/home.css
ifpd/interface/css/style.css
ifpd/interface/fonts/fa-brands-400.eot
ifpd/interface/fonts/fa-brands-400.svg
ifpd/interface/fonts/fa-brands-400.ttf
ifpd/interface/fonts/fa-brands-400.woff
ifpd/interface/fonts/fa-brands-400.woff2
ifpd/interface/fonts/fa-regular-400.eot
ifpd/interface/fonts/fa-regular-400.svg
ifpd/interface/fonts/fa-regular-400.ttf
ifpd/interface/fonts/fa-regular-400.woff
ifpd/interface/fonts/fa-regular-400.woff2
ifpd/interface/fonts/fa-solid-900.eot
ifpd/interface/fonts/fa-solid-900.svg
ifpd/interface/fonts/fa-solid-900.ttf
ifpd/interface/fonts/fa-solid-900.woff
ifpd/interface/fonts/fa-solid-900.woff2
ifpd/interface/images/favicon.ico
ifpd/interface/images/title_background.png
ifpd/interface/js/bootstrap.min.js
ifpd/interface/js/clipboard.min.js
ifpd/interface/js/jquery.min.js
ifpd/interface/js/popper.min.js
ifpd/interface/views/footer.tpl.html
ifpd/interface/views/header.tpl.html
ifpd/interface/views/home_default.tpl.html
ifpd/query.py
ifpd/scripts/__init__.py
ifpd/scripts/arguments.py
ifpd/scripts/dbchk.py
ifpd/scripts/ifpd.py
ifpd/scripts/mkdb.py
ifpd/scripts/query/__init__.py
ifpd/scripts/query/probe.py
ifpd/scripts/query/query.py
ifpd/scripts/query/set.py
ifpd/scripts/serve.py
ifpd/sections/__init__.py
ifpd/sections/app.py
ifpd/sections/probe_design/__init__.py
ifpd/sections/probe_design/app.py
ifpd/sections/probe_design/css/home.css
ifpd/sections/probe_design/css/query.css
ifpd/sections/probe_design/css/style.css
ifpd/sections/probe_design/enquirer.py
ifpd/sections/probe_design/query.py
ifpd/sections/probe_design/queue.py
ifpd/sections/probe_design/routes.py
ifpd/sections/probe_design/views/candidate_probe.tpl.html
ifpd/sections/probe_design/views/candidate_set.tpl.html
ifpd/sections/probe_design/views/candidate_set_probe.tpl.html
ifpd-2.1.1.post2.dist-info/entry_points.txt
ifpd-2.1.1.post2.dist-info/LICENSE
ifpd-2.1.1.post2.dist-info/WHEEL
ifpd-2.1.1.post2.dist-info/METADATA
ifpd-2.1.1.post2.dist-info/RECORD
