Metadata-Version: 2.1
Name: ifpd
Version: 2.1.1.post2
Summary: An iFISH probe design pipeline, with web interface included.
Home-page: https://github.com/ggirelli/iFISH-Probe-Design
License: MIT
Keywords: biology,cell,DNA,RNA,FISH,fluorescence,hybridization
Author: Gabriele Girelli
Author-email: gigi.ga90@gmail.com
Requires-Python: >=3.7.1,<4.0.0
Classifier: Development Status :: 5 - Production/Stable
Classifier: Intended Audience :: Science/Research
Classifier: License :: OSI Approved :: MIT License
Classifier: Operating System :: POSIX :: Linux
Classifier: Operating System :: Unix
Classifier: Programming Language :: Python :: 3
Classifier: Programming Language :: Python :: 3.7
Classifier: Programming Language :: Python :: 3.8
Classifier: Programming Language :: Python :: 3.9
Classifier: Topic :: Scientific/Engineering :: Bio-Informatics
Requires-Dist: Paste (>=3.5.0,<4.0.0)
Requires-Dist: bottle (>=0.12.19,<0.13.0)
Requires-Dist: joblib (>=1.0.1,<2.0.0)
Requires-Dist: matplotlib (>=3.3.4,<4.0.0)
Requires-Dist: numpy (>=1.20.1,<2.0.0)
Requires-Dist: pandas (>=1.2.2,<2.0.0)
Requires-Dist: pytest (>=6.2.2,<7.0.0)
Requires-Dist: rich (>=9.10,<11.0)
Requires-Dist: scipy (>=1.6.0,<2.0.0)
Project-URL: Repository, https://github.com/ggirelli/iFISH-Probe-Design
